{
  "spider": "./ttkx.jar",
  "wallpaper": "https://tuapi.eees.cc/api.php?category=fengjing&type=302",
  "lives": [
    {
      "name": "live",
      "type": 0,
      "url": "./lib/live1.txt",
      "epg": "http://epg.112114.eu.org/?ch={name}&date={date}",
      "logo": "https://epg.112114.xyz/bingimg/logo/{name}.png"
    }
  ],
  "sites": [
    {
      "key": "豆瓣",
      "name": "乡村最美妞祝大家龙年大发",
      "type": 3,
      "api": "./drpy2.min.js",
      "searchable": 0,
      "quickSearch": 0,
      "filterable": 0,
      "ext": "./豆瓣.js"
    },
    {
      "key": "csp_LocalFile",
      "name": "💻本地视频",
      "type": 3,
      "api": "csp_LocalFile",
      "searchable": 0,
      "quickSearch": 0,
      "filterable": 0,
      "type_flag": 0
    },
{
      "key": "csp_KungFu404",
      "name": "🌥️┃Open原画┃设置",
      "type": 3,
      "api": "csp_KungFu404",
      "jar": "./jar/alibaba.jar",
      "searchable": 0,
      "filterable": 0,
      "ext": "http://127.0.0.1:9978/file/tvbox/token.txt+4k|fhd|auto"
    },
    {
      "key": "直播转点播",
      "name": "📺︎电视IJK点播",
      "type": 3,
      "api": "./js/zbzdb.js",
      "searchable": 1,
      "quickSearch": 0,
      "filterable": 0,
      "ext": "./json/zb.json"
    },
    {
      "key": "荐片",
      "name": "🌺荐片┃秒播",
      "type": 3,
      "api": "./drpy2.min.js",
      "ext": "./js/jianpian.js"
    },
    {
      "key": "开心HK影视",
      "name": "🌺开心HK影视",
      "type": 3,
      "api": "csp_XBPQ",
      "searchable": 1,
      "quickSearch": 1,
      "filterable": 1,
      "ext": "./json/开心HK影视.json"
    },
        {
      "key": "业余采集A",
      "name": "🌺业余无广",
      "type": 1,
      "api": "http://540734621.xyz/api.php/provide/vod/",
      "playUrl": "json:http://uutb.centos.chat/jsonwjm.php/?url=",
      "searchable": 1,
      "quickSearch": 1,
      "filterable": 1,
      "changeable": 1,
      "categories": [
        "短剧",
        "电影",
        "国内剧",
        "欧美剧",
        "港台剧",
        "日韩剧",
        "海外剧",
        "国内电影",
        "欧美电影",
        "港台电影",
        "日韩电影",
        "国内动漫",
        "日韩动漫",
        "欧美动漫",
        "国内综艺",
        "欧美综艺",
        "日韩综艺",
        "纪录片",
        "音乐",
        "体育"
      ]
    },
    {
      "key": "csp_xBPQ_小茶狐",
      "name": "🌺小茶狐",
      "type": 3,
      "api": "csp_XBPQ",
      "searchable": 1,
      "quickSearch": 1,
      "filterable": 1,
      "ext": "./json/小茶狐.json"
    },
    {
      "key": "玩我哥哥",
      "name": "🌺玩我|哥哥",
      "type": 3,
      "api": "csp_XYQHikerAL",
      "searchable": 1,
      "quickSearch": 1,
      "filterable": 1,
      "ext": "./json/玩我哥哥.json"
    },
    {
      "key": "玩偶哥哥",
      "name": "🌺玩偶|哥哥",
      "type": 3,
      "api": "csp_XYQHikerAL",
      "searchable": 1,
      "quickSearch": 1,
      "filterable": 1,
      "ext": "./json/玩偶哥哥.json"
    },
    {
      "key": "短剧",
      "name": "🌺上头┃短剧",
      "type": 3,
      "api": "csp_Djuu",
      "searchable": 1,
      "quickSearch": 1,
      "changeable": 1
    },
    {
      "key": "酷看",
      "name": "🌺酷看┃秒播",
      "type": 3,
      "api": "csp_Kkys",
      "timeout": 15,
      "searchable": 1,
      "quickSearch": 1,
      "changeable": 1
    },
    {
      "key": "原创",
      "name": "🌺原创┃无广",
      "type": 3,
      "api": "csp_YCyz",
      "timeout": 15,
      "searchable": 1,
      "quickSearch": 1,
      "changeable": 1
    },
    {
      "key": "苹果",
      "name": "🌺苹果┃无广",
      "type": 3,
      "api": "csp_LiteApple",
      "searchable": 1,
      "quickSearch": 1,
      "changeable": 1
    },
    {
      "key": "白嫖",
      "name": "🌺白飘┃无广",
      "type": 3,
      "api": "csp_BaiPiao",
      "playerType": 2,
      "searchable": 1,
      "quickSearch": 1,
      "changeable": 1,
      "ext": "https://www.baipiaoys.com:9092/"
    },
    {
      "key": "视觉",
      "name": "🌺视觉┃直连",
      "type": 3,
      "api": "csp_Xinsj",
      "timeout": 15,
      "searchable": 1,
      "quickSearch": 1,
      "changeable": 1,
      "ext": "https://www.80yy3.com/"
    },
    {
      "key": "厂长",
      "name": "🌺厂长┃无广",
      "type": 3,
      "api": "csp_NewCz",
      "timeout": 15,
      "playerType": 2,
      "searchable": 1,
      "quickSearch": 1,
      "changeable": 1,
      "ext": "https://www.czys.top/"
    },
    {
      "key": "七七",
      "name": "🌺七七┃秒播",
      "type": 3,
      "api": "csp_Kunyu77",
      "timeout": 15,
      "searchable": 1,
      "quickSearch": 1,
      "changeable": 1
    },
    {
      "key": "南瓜",
      "name": "🌺南瓜┃App",
      "type": 3,
      "api": "csp_NanGua",
      "timeout": 15,
      "playerType": 2,
      "searchable": 1,
      "quickSearch": 1,
      "changeable": 1
    },
    {
      "key": "糯米",
      "name": "🌺糯米┃秒播",
      "type": 3,
      "api": "csp_Nmys",
      "timeout": 15,
      "searchable": 1,
      "quickSearch": 1,
      "changeable": 1,
      "ext": "./json/nmys.json"
    },
    {
      "key": "低端",
      "name": "🌺低端┃外剧",
      "type": 3,
      "api": "csp_Ddrk",
      "playerType": "2",
      "searchable": 1,
      "quickSearch": 1,
      "changeable": 1
    },
    {
      "key": "萌米",
      "name": "🌺萌米┃App",
      "type": 3,
      "api": "csp_AppTT",
      "timeout": 15,
      "playerType": 1,
      "ext": "AO7TcBkd8Iifux0Y8Qze6tVlMg=="
    },
    {
      "key": "比特",
      "name": "🌺比特┃秒播",
      "type": 3,
      "api": "csp_Bttwoo",
      "searchable": 1,
      "quickSearch": 1,
      "changeable": 1
    },
    {
      "key": "zxzj",
      "name": "🌺在线┃外剧",
      "type": 3,
      "api": "csp_Zxzj",
      "timeout": 15,
      "searchable": 1,
      "quickSearch": 1,
      "changeable": 1,
      "ext": "https://www.zxzja.com/"
    },
    {
      "key": "Lib",
      "name": "🌺立播┃直连",
      "type": 3,
      "api": "csp_Libvio",
      "timeout": 15,
      "searchable": 1,
      "quickSearch": 1,
      "changeable": 1,
      "ext": "https://www.libvio.pw/"
    },
    {
      "key": "csp_红狐狸影视",
      "name": "🌺红狐狸影视",
      "type": 3,
      "api": "csp_XBPQ",
      "ext": {
        "分类url": "https://honghuli.com/leibiao/{cateId}-{area}-------{catePg}---{year}.html",
        "分类": "电影$1#电视剧$2#综艺$3#动漫$4"
      }
    },
    {
      "key": "csp_xBPQ可可",
      "name": "🌺可可影视",
      "type": 3,
      "api": "csp_XBPQ",
      "searchable": 1,
      "quickSearch": 1,
      "filterable": 1,
      "ext": "./json/可可影视.json"
    },
    {
      "key": "csp_XYQBiu_骚火VIP",
      "name": "🌺骚火┃秒播",
      "type": 3,
      "api": "csp_XBPQ",
      "searchable": 1,
      "quickSearch": 1,
      "filterable": 1,
      "ext": "./json/shyyVIP.json"
    },
    {
      "key": "赘婿影视",
      "name": "🌺赘婿影视",
      "type": 3,
      "api": "csp_XBPQ",
      "searchable": 1,
      "quickSearch": 1,
      "filterable": 1,
      "ext": {
        "数组": "video-img lazyload&&</p>",
        "副标题": "mr-xs-0\">&&</span>",
        "简介": "entry-content clearfix\">&&</p>",
        "搜索url": "https://zhuixu.cc/Kansearch/-------------/?wd=",
        "线路数组": "data-target=\"#ewave-playlist-&&</li>",
        "线路标题": ">&&</a >",
        "播放数组": "<ul class=\"row ewave-tab-content ewave-playlist-content&&</ul>",
        "跳转播放链接": "var player_*\"url\":\"&&\"",
        "分类url": "https://zhuixu.cc/type/{cateId}-{catePg}/",
        "分类": "剧集$2#电影$1#番剧$4#纪录$39#短剧$44#体育$45#娱乐$46#解说$48"
      }
    },
    {
      "key": "农民影视",
      "name": "🌺农民┃秒播",
      "type": 3,
      "api": "csp_XBPQ",
      "searchable": 1,
      "quickSearch": 1,
      "filterable": 1,
      "ext": "./json/农民影视.json"
    },
    {
      "key": "奈飞影视",
      "name": "🌺鸭奈飞┃秒播",
      "type": 3,
      "api": "csp_XYQHiker",
      "searchable": 1,
      "quickSearch": 1,
      "filterable": 1,
      "ext": "./json/ynfys.json"
    },
    {
      "key": "奈飞中文",
      "name": "🌺奈飞┃秒播",
      "type": 3,
      "api": "csp_XYQHiker",
      "searchable": 1,
      "quickSearch": 1,
      "filterable": 1,
      "ext": "./json/nfzw.json"
    },
    {
      "key": "csp_xBPQ_九八",
      "name": "🌺九八┃秒播",
      "type": 3,
      "api": "csp_XBPQ",
      "searchable": 1,
      "quickSearch": 1,
      "filterable": 1,
      "ext": "./json/98.json"
    },
    {
      "key": "热播之家",
      "name": "🌺热播之家",
      "type": 3,
      "api": "csp_XYQHiker",
      "searchable": 1,
      "quickSearch": 1,
      "filterable": 1,
      "ext": "./json/rebozj.json"
    },
    {
      "key": "TVB云播",
      "name": "🌺TVB云播",
      "type": 3,
      "api": "csp_XBPQ",
      "searchable": 1,
      "quickSearch": 1,
      "filterable": 1,
      "ext": "./json/TVB.json"
    },
    {
      "key": "达达龟",
      "name": "🌺达龟┃秒播",
      "type": 3,
      "api": "csp_XBPQ",
      "searchable": 1,
      "quickSearch": 1,
      "filterable": 0,
      "ext": "./json/dadagui.json"
    },
    {
      "key": "csp_xBPQ_疯狗",
      "name": "🌺疯狗┃秒播",
      "type": 3,
      "api": "csp_XBPQ",
      "searchable": 1,
      "quickSearch": 1,
      "filterable": 1,
      "ext": "./json/fgys.json"
    },
    {
      "key": "csp_vs",
      "name": "🌺VS┃秒播",
      "type": 3,
      "api": "csp_XBPQ",
      "searchable": 1,
      "quickSearch": 1,
      "filterable": 1,
      "ext": "./json/vsys.json"
    },
    {
      "key": "348影视",
      "name": "🌺348┃秒播",
      "type": 3,
      "api": "csp_XBPQ",
      "searchable": 1,
      "quickSearch": 1,
      "filterable": 1,
      "ext": "./json/348.json"
    },
    {
      "key": "csp_五五",
      "name": "🌺五五┃秒播",
      "type": 3,
      "api": "csp_XBPQ",
      "searchable": 1,
      "quickSearch": 1,
      "filterable": 1,
      "ext": "./json/55.json"
    },
    {
      "key": "兄弟影视",
      "name": "🌺兄弟┃秒播",
      "type": 3,
      "api": "csp_XYQHiker",
      "searchable": 1,
      "quickSearch": 1,
      "filterable": 1,
      "ext": "./json/xdys.json"
    },
    {
      "key": "csp_盒子",
      "name": "🌺盒子┃秒播",
      "type": 3,
      "api": "csp_XBPQ",
      "searchable": 1,
      "quickSearch": 1,
      "filterable": 1,
      "ext": "./json/hezi.json"
    },
    {
      "key": "csp_Free",
      "name": "🌺Free┃秒播",
      "type": 3,
      "api": "csp_XBPQ",
      "searchable": 1,
      "quickSearch": 1,
      "filterable": 1,
      "ext": "./json/Free.json"
    },
    {
      "key": "csp_星辰",
      "name": "🌺星辰┃秒播",
      "type": 3,
      "api": "csp_XBPQ",
      "searchable": 1,
      "quickSearch": 1,
      "filterable": 1,
      "ext": "./json/xcys.json"
    },
    {
      "key": "csp_黑狐",
      "name": "🌺黑狐┃秒播",
      "type": 3,
      "api": "csp_XBPQ",
      "searchable": 1,
      "quickSearch": 1,
      "filterable": 1,
      "ext": "./json/heihu.json"
    },
    {
      "key": "csp_xBPQ_奇优",
      "name": "🌺奇优┃秒播",
      "type": 3,
      "api": "csp_XBPQ",
      "searchable": 1,
      "quickSearch": 1,
      "filterable": 1,
      "ext": "./json/qiyou.json"
    },
    {
      "key": "七新影视",
      "name": "🌺七新┃秒播",
      "type": 3,
      "api": "csp_XYQHiker",
      "searchable": 1,
      "quickSearch": 1,
      "filterable": 1,
      "ext": "./json/qixinyingshi.json"
    },
    {
      "key": "VIP影视",
      "name": "🌺VIP┃秒播",
      "type": 3,
      "api": "csp_XPath",
      "searchable": 1,
      "quickSearch": 1,
      "filterable": 0,
      "ext": "./json/VIPyingshi.json"
    },
    {
      "key": "圣城影视",
      "name": "🌺圣城┃2K",
      "type": 3,
      "api": "csp_XBPQ",
      "searchable": 1,
      "quickSearch": 1,
      "filterable": 1,
      "ext": "./json/sc1080.json"
    },
    {
      "key": "米爱影视",
      "name": "🌺米爱┃2K",
      "type": 3,
      "api": "csp_XBPQ",
      "searchable": 1,
      "quickSearch": 1,
      "filterable": 1,
      "ext": "./json/miaiys.json"
    },
    {
      "key": "csp_视觉",
      "name": "🌺视觉┃2K",
      "type": 3,
      "api": "csp_XBPQ",
      "searchable": 1,
      "quickSearch": 1,
      "filterable": 1,
      "ext": "./json/xinshijue.json"
    },
    {
      "key": "csp_蛋蛋",
      "name": "🌺蛋蛋┃2K",
      "type": 3,
      "api": "csp_XBPQ",
      "searchable": 1,
      "quickSearch": 1,
      "filterable": 1,
      "ext": "./json/dandan.json"
    },
    {
      "key": "HDmoli",
      "name": "🌺魔力高清",
      "type": 3,
      "api": "csp_XBPQ",
      "searchable": 1,
      "quickSearch": 1,
      "filterable": 1,
      "ext": "./json/HDmoli.json"
    },
    {
      "key": "策驰影院",
      "name": "🌺策驰影院",
      "type": 3,
      "api": "csp_XBPQ",
      "searchable": 1,
      "quickSearch": 1,
      "filterable": 1,
      "ext": "./json/cechi.json"
    },
    {
      "key": "csp_Voflix",
      "name": "🌺Voflix",
      "type": 3,
      "api": "csp_XBPQ",
      "searchable": 1,
      "quickSearch": 1,
      "filterable": 1,
      "ext": "./json/voflix.json"
    },
    {
      "key": "Vidhub视频",
      "name": "🌺视频库",
      "type": 3,
      "api": "csp_XBPQ",
      "searchable": 1,
      "quickSearch": 1,
      "filterable": 1,
      "ext": "./json/Vidhub.json"
    },
    {
      "key": "石榴影视",
      "name": "🌺石榴影视",
      "type": 3,
      "api": "csp_XBPQ",
      "searchable": 1,
      "quickSearch": 1,
      "filterable": 1,
      "ext": "./json/shiliu.json"
    },
    {
      "key": "VIP影视",
      "name": "🌺VIP┃2K",
      "type": 3,
      "api": "csp_XPath",
      "searchable": 1,
      "quickSearch": 1,
      "filterable": 0,
      "ext": "./json/VIPyingshi.json"
    },
    {
      "key": "lzi",
      "name": "🌺量子资源",
      "type": 3,
      "api": "csp_XBPQ",
      "searchable": 1,
      "quickSearch": 1,
      "filterable": 1,
      "ext": "./json/liangzi.json"
    },
    {
      "key": "非凡资源",
      "name": "🌺非凡资源",
      "type": 3,
      "api": "csp_XBPQ",
      "searchable": 1,
      "quickSearch": 1,
      "filterable": 1,
      "ext": "./json/ffzy.json"
    },
    {
      "key": "拳皇争霸",
      "name": "🌺拳皇争霸",
      "type": 3,
      "api": "./drpy2.min.js",
      "ext": "./js/quanhuang.js"
    },
    {
      "key": "奇虎影视",
      "name": "🌺奇虎影视",
      "type": 1,
      "api": "https://caiji.qhzyapi.com/api.php/provide/vod/",
      "playerType": 1,
      "searchable": 1,
      "quickSearch": 1,
      "filterable": 1,
      "categories": [
        "动作片",
        "战争片",
        "国产剧",
        "港台剧",
        "日韩剧",
        "欧美剧",
        "国产动漫",
        "动漫",
        "综艺",
        "动画片",
        "短剧",
        "喜剧片",
        "爱情片",
        "科幻片",
        "恐怖片",
        "剧情片",
        "灾难片",
        "悬疑片",
        "犯罪片",
        "奇幻片",
        "伦理片",
        "纪录片"
      ]
    },
    {
      "key": "csp_xml_爱坤",
      "name": "🌺爱坤┃2K",
      "type": 1,
      "api": "https://ikunzyapi.com/api.php/provide/vod",
      "searchable": 1,
      "quickSearch": 1,
      "filterable": 1,
      "playurl": "json:https://www.ikdmjx.com/?url=",
      "categories": [
        "动作片",
        "国产剧",
        "喜剧片",
        "科幻片",
        "恐怖片",
        "爱情片",
        "剧情片",
        "战争片",
        "纪录片",
        "动漫电影",
        "欧美剧",
        "港澳剧",
        "韩剧",
        "台湾剧",
        "日剧",
        "海外剧",
        "泰剧",
        "体育",
        "国产动漫",
        "日韩动漫",
        "欧美动漫",
        "港台动漫",
        "海外动漫",
        "大陆综艺",
        "港台综艺",
        "日韩综艺",
        "欧美综艺",
        "伦理片"
      ]
    },
    {
      "key": "csp_xml_红牛",
      "name": "🌺红牛┃2K",
      "type": 1,
      "api": "https://www.hongniuzy2.com/api.php/provide/vod/",
      "searchable": 1,
      "quickSearch": 1,
      "filterable": 1,
      "playurl": "json:http://jx.84jia.com/m3u8ts.php?url=",
      "categories": [
        "动作片",
        "国产剧",
        "喜剧片",
        "科幻片",
        "恐怖片",
        "爱情片",
        "剧情片",
        "战争片",
        "纪录片",
        "动漫电影",
        "欧美剧",
        "犯罪片",
        "港澳剧",
        "韩剧",
        "泰剧",
        "台湾剧",
        "日剧",
        "海外剧",
        "其他片",
        "悬疑片",
        "奇幻片",
        "动画片",
        "体育赛事",
        "国产动漫",
        "日本动漫",
        "欧美动漫",
        "港台动漫",
        "海外动漫",
        "大陆综艺",
        "港台综艺",
        "日韩综艺",
        "欧美综艺"
      ]
    },
    {
      "key": "索尼资源",
      "name": "🌺索尼┃2K",
      "type": 1,
      "api": "https://suoniapi.com/api.php/provide/vod/from/snm3u8/",
      "searchable": 1,
      "quickSearch": 1,
      "filterable": 1,
      "playurl": "json:http://jx.84jia.com/m3u8ts.php?url=",
      "categories": [
        "动作片",
        "国产剧",
        "喜剧片",
        "爱情片",
        "科幻片",
        "恐怖片",
        "剧情片",
        "战争片",
        "欧美剧",
        "韩剧",
        "日剧",
        "港剧",
        "台剧",
        "泰剧",
        "海外剧",
        "纪录片",
        "大陆综艺",
        "日韩综艺",
        "港台综艺",
        "欧美综艺",
        "国产动漫",
        "日韩动漫",
        "欧美动漫",
        "动画片",
        "港台动漫",
        "海外动漫",
        "演唱会",
        "体育赛事",
        "篮球",
        "足球",
        "斯诺克"
      ]
    },
    {
      "key": "csp_xml_新浪",
      "name": "🌺新浪┃2K",
      "type": 1,
      "api": "https://api.xinlangapi.com/xinlangapi.php/provide//vod/",
      "searchable": 1,
      "quickSearch": 1,
      "filterable": 1,
      "playurl": "json:http://jx.84jia.com/m3u8ts.php?url=",
      "categories": [
        "动作片",
        "大陆剧",
        "喜剧片",
        "科幻片",
        "恐怖片",
        "爱情片",
        "剧情片",
        "战争片",
        "纪录片",
        "动漫电影",
        "欧美剧",
        "港澳剧",
        "韩剧",
        "台湾剧",
        "日剧",
        "海外剧",
        "泰剧",
        "体育",
        "国产动漫",
        "日韩动漫",
        "欧美动漫",
        "港台动漫",
        "海外动漫",
        "大陆综艺",
        "港台综艺",
        "日韩综艺",
        "欧美综艺"
      ]
    },
    {
      "key": "高清资源网",
      "name": "🌺高清┃2K",
      "type": 1,
      "api": "https://api.1080zyku.com/inc/apijson.php",
      "searchable": 1,
      "quickSearch": 1,
      "filterable": 1,
      "playurl": "json:http://jx.84jia.com/m3u8ts.php?url=",
      "categories": [
        "动作片",
        "国产剧",
        "喜剧片",
        "爱情片",
        "科幻片",
        "恐怖片",
        "剧情片",
        "战争片",
        "记录片",
        "欧美剧",
        "日本剧",
        "泰国剧",
        "韩国剧",
        "台湾剧",
        "香港剧",
        "大陆综艺",
        "港台综艺",
        "日韩综艺",
        "欧美综艺",
        "国产动漫",
        "日韩动漫",
        "欧美动漫"
      ]
    },
    {
      "key": "麻衣呀呼",
      "name": "🌺麻衣呀呼",
      "type": 3,
      "api": "csp_XBPQ",
      "searchable": 1,
      "quickSearch": 1,
      "filterable": 1,
      "ext": "./json/mayiyahu.json"
    },
    {
      "key": "49zy",
      "name": "🌺四九资源",
      "type": 1,
      "api": "https://49zyw.com/api.php/provide/vod/?ac=list",
      "searchable": 1,
      "quickSearch": 1,
      "filterable": 1,
      "changeable": 1,
      "categories": [
        "国产剧",
        "纪录片",
        "欧美剧",
        "香港剧",
        "动作片",
        "爱情片",
        "科幻片",
        "恐怖片",
        "剧情片",
        "战争片",
        "喜剧片",
        "动画片",
        "犯罪片",
        "韩国剧",
        "动漫",
        "电影",
        "大陆综艺",
        "港台综艺",
        "日韩综艺",
        "欧美综艺",
        "台湾剧",
        "国产动漫",
        "日本动漫",
        "欧美动漫",
        "泰国剧",
        "日剧",
        "电影解说",
        "奇幻片",
        "灾难片",
        "悬疑片",
        "其他片",
        "体育赛事",
        "海外剧"
      ]
    },
    {
      "key": "csp_xml_百度",
      "name": "🌺百度资源",
      "type": 1,
      "api": "https://api.apibdzy.com/api.php/provide/vod/?ac=list",
      "searchable": 1,
      "quickSearch": 1,
      "filterable": 1,
      "playurl": "json:http://jx.84jia.com/m3u8ts.php?url=",
      "categories": [
        "动作片",
        "喜剧片",
        "科幻片",
        "恐怖片",
        "爱情片",
        "剧情片",
        "战争片",
        "纪录片",
        "动画电影",
        "大陆剧",
        "欧美剧",
        "犯罪片",
        "港澳剧",
        "韩剧",
        "泰剧",
        "台湾剧",
        "日剧",
        "海外剧",
        "其他片",
        "悬疑片",
        "奇幻片",
        "动画片",
        "体育赛事",
        "国产动漫",
        "日韩动漫",
        "欧美动漫",
        "港台动漫",
        "海外动漫",
        "大陆综艺",
        "港台综艺",
        "日韩综艺",
        "欧美综艺"
      ]
    },
    {
      "key": "爱奇异",
      "name": "🌺爱奇艺(官)",
      "type": 3,
      "api": "./drpy2.min.js",
      "ext": "./js/奇珍异兽.js"
    },
    {
      "key": "优酷",
      "name": "🌺优酷(官)",
      "type": 3,
      "api": "./drpy2.min.js",
      "ext": "./js/优酷.js"
    },
    {
      "key": "腾讯",
      "name": "🌺腾讯(官)",
      "type": 3,
      "api": "./drpy2.min.js",
      "ext": "./js/腾云驾雾.js"
    },
    {
      "key": "芒果",
      "name": "🌺芒果(官)",
      "type": 3,
      "api": "./drpy2.min.js",
      "ext": "./js/百忙无果.js"
    },
    {
      "key": "搜狗",
      "name": "🌺搜狗(官)",
      "type": 3,
      "api": "./drpy2.min.js",
      "ext": "./js/caigou.js"
    },
    {
      "key": "360影视",
      "name": "🌺360影视(官)",
      "type": 3,
      "api": "csp_SP360",
      "searchable": 1,
      "quickSearch": 1,
      "filterable": 1,
      "changeable": 0
    },
    {
      "key": "csp_Mp4Mov",
      "name": "🧲Mp4电影",
      "type": 3,
      "api": "csp_Mp4Mov",
      "searchable": 1,
      "quickSearch": 1,
      "filterable": 1
    },
    {
      "key": "csp_New6v",
      "name": "🧲新6V",
      "type": 3,
      "api": "csp_New6v",
      "searchable": 1,
      "quickSearch": 1,
      "filterable": 1,
      "ext": "https://www.xb6v.com"
    },
    {
      "key": "csp_SeedHub",
      "name": "🧲SeedHub",
      "type": 3,
      "api": "csp_SeedHub",
      "searchable": 1,
      "quickSearch": 1,
      "filterable": 1
    },
    {
      "key": "csp_KubaCL",
      "name": "🧲酷吧电影",
      "type": 3,
      "api": "csp_KubaCL",
      "searchable": 1,
      "quickSearch": 1,
      "filterable": 1
    },
    {
      "key": "csp_MeijuMi",
      "name": "🧲美剧迷",
      "type": 3,
      "api": "csp_MeijuMi",
      "searchable": 1,
      "quickSearch": 1,
      "filterable": 1
    },
    {
      "key": "csp_Xunlei8",
      "name": "🧲迅雷吧",
      "type": 3,
      "api": "csp_Xunlei8",
      "searchable": 1,
      "quickSearch": 1,
      "filterable": 1
    },
    {
      "key": "土豆阿里",
      "name": "🌺土豆阿里",
      "type": 3,
      "api": "csp_XYQHikerAL",
      "searchable": 1,
      "quickSearch": 1,
      "filterable": 1,
      "ext": "./json/土豆阿里.json"
    },
    {
      "key": "多多阿里",
      "name": "🌺多多阿里",
      "type": 3,
      "api": "csp_XYQHikerAL",
      "searchable": 1,
      "quickSearch": 1,
      "filterable": 1,
      "ext": "./json/玩你老哥.json"
    },
    {
      "key": "csp_AliPS",
      "name": "📀喵狸盘搜(搜索)",
      "type": 3,
      "api": "csp_AliPS",
      "searchable": 1,
      "quickSearch": 1,
      "filterable": 0,
      "ext": "http://127.0.0.1:9978/file/XYQTVBox/alitoken.txt"
    },
    {
      "key": "csp_XYQHiker_影搜",
      "name": "📀影搜(搜索)",
      "type": 3,
      "api": "csp_XYQHiker",
      "searchable": 1,
      "quickSearch": 1,
      "filterable": 1,
      "ext": "./json/影搜.json"
    },
    {
      "key": "csp_Upyunso",
      "name": "📀UP云搜(搜索)",
      "type": 3,
      "api": "csp_Upyunso",
      "searchable": 1,
      "quickSearch": 1,
      "filterable": 0,
      "ext": "http://127.0.0.1:9978/file/XYQTVBox/alitoken.txt"
    },
    {
      "key": "csp_XYQHikerAL_云盘资源",
      "name": "📀云盘资源(搜索)",
      "type": 3,
      "api": "csp_XYQHikerAL",
      "searchable": 1,
      "quickSearch": 1,
      "filterable": 1,
      "ext": "./json/云盘资源.json"
    },
    {
      "key": "演唱会",
      "name": "🎸演唱会",
      "type": 3,
      "api": "csp_Bili",
      "searchable": 1,
      "quickSearch": 1,
      "filterable": 1,
      "ext": "./json/哔哩演唱会.json"
    },
    {
      "key": "csp_XBPQ_短视频",
      "name": "☘️短视频",
      "type": 3,
      "api": "csp_XBPQ",
      "searchable": 0,
      "quickSearch": 0,
      "filterable": 1,
      "ext": "./json/duanshipin.json"
    },
    {
      "key": "88js",
      "name": "⚽ 88┃看球",
      "type": 3,
      "api": "csp_Kanqiu",
      "style": {
        "type": "list"
      },
      "searchable": 0,
      "quickSearch": 0,
      "changeable": 0
    },
    {
      "key": "js_310直播",
      "name": "🥎┃三一┃直播",
      "type": 3,
      "api": "./lib/drpy2.min.js",
      "searchable": 1,
      "quickSearch": 1,
      "filterable": 0,
      "ext": "./js/310.js"
    },
    {
      "key": "csp_XPath_企鹅体育",
      "name": "🐧企鹅体育",
      "type": 3,
      "api": "csp_XPath",
      "style": {
        "type": "rect",
        "ratio": 1.597
      },
      "searchable": 0,
      "quickSearch": 0,
      "changeable": 0,
      "ext": "./json/qietiyu.json"
    },
    {
      "key": "csp_Yj1211",
      "name": "📡JustLive",
      "type": 3,
      "api": "csp_Yj1211",
      "playerType": 1,
      "searchable": 1,
      "quickSearch": 1,
      "filterable": 1
    },
    {
      "key": "JRKAN直播",
      "name": "⚽JRKAN直播",
      "type": 3,
      "api": "./drpy2.min.js",
      "searchable": 0,
      "quickSearch": 0,
      "filterable": 1,
      "ext": "./js/jrk.js"
    },
    {
      "key": "虎牙直播",
      "name": "🐯虎牙直播",
      "type": 3,
      "api": "./drpy2.min.js",
      "searchable": 0,
      "quickSearch": 0,
      "filterable": 1,
      "ext": "./js/huyazhibo.js"
    },
    {
      "key": "斗鱼直播",
      "name": "🐟斗鱼直播",
      "type": 3,
      "api": "./drpy2.min.js",
      "searchable": 0,
      "quickSearch": 0,
      "filterable": 1,
      "ext": "./js/douyu.js"
    },
    {
      "key": "哔哩哔哩",
      "name": "🅱️哔哩大全",
      "type": 3,
      "api": "csp_Bili",
      "searchable": 1,
      "quickSearch": 1,
      "filterable": 1,
      "ext": "./json/Bili.json"
    },
    {
      "key": "哔哩直播",
      "name": "🅱️哔哩直播",
      "type": 3,
      "api": "./drpy2.min.js",
      "searchable": 0,
      "quickSearch": 0,
      "filterable": 1,
      "ext": "./json/blzb.js"
    },
    {
      "key": "csp_Bili短剧",
      "name": "🅱️哔哩短剧",
      "type": 3,
      "api": "csp_Bili",
      "searchable": 0,
      "quickSearch": 0,
      "filterable": 1,
      "ext": "./json/Bili短剧.json"
    },
    {
      "key": "学习园地",
      "name": "📚┃学习园地",
      "type": 3,
      "api": "csp_Bili",
      "searchable": 1,
      "quickSearch": 1,
      "filterable": 1,
      "ext": "./json/Blixt.json"
    },
    {
      "key": "学外语",
      "name": "📚┃学外语",
      "type": 3,
      "api": "csp_Bili",
      "searchable": 1,
      "quickSearch": 1,
      "filterable": 1,
      "ext": "./json/waiyu.json"
    },
    {
      "key": "js_i275听书",
      "name": "📚️听书┃i275",
      "type": 3,
      "api": "./drpy2.min.js",
      "changeable": 0,
      "style": {
        "type": "rect",
        "ratio": 1
      },
      "ext": "./js/i275.js"
    },
    {
      "key": "js_博看听书",
      "name": "📚️听书┃博看",
      "type": 3,
      "api": "./drpy2.min.js",
      "changeable": 0,
      "style": {
        "type": "rect",
        "ratio": 1
      },
      "ext": "./js/bokan.js"
    },
    {
      "key": "js_海洋听书",
      "name": "📚️听书┃海洋",
      "type": 3,
      "api": "./drpy2.min.js",
      "changeable": 0,
      "style": {
        "type": "rect",
        "ratio": 1
      },
      "ext": "./js/sea.js"
    },
    {
      "key": "js_六月听书",
      "name": "📚️听书┃六月",
      "type": 3,
      "api": "./drpy2.min.js",
      "changeable": 0,
      "style": {
        "type": "rect",
        "ratio": 1
      },
      "ext": "./js/6yue.js"
    },
    {
      "key": "js_听书网",
      "name": "📚️听书┃天天",
      "type": 3,
      "api": "./drpy2.min.js",
      "changeable": 0,
      "style": {
        "type": "rect",
        "ratio": 1
      },
      "ext": "./js/tingshu.js"
    },
    {
      "key": "js_有声小说",
      "name": "📚️听书┃有声",
      "type": 3,
      "api": "./drpy2.min.js",
      "changeable": 0,
      "style": {
        "type": "rect",
        "ratio": 1
      },
      "ext": "./js/有声小说吧.js"
    },
    {
      "key": "js_中华听书网",
      "name": "📚️听书┃中华",
      "type": 3,
      "api": "./drpy2.min.js",
      "changeable": 0,
      "style": {
        "type": "rect",
        "ratio": 1
      },
      "ext": "./js/zhonghua.js"
    },
    {
      "key": "DJ呦呦音乐网",
      "name": "🎧DJ呦呦音乐",
      "type": 3,
      "api": "csp_XYQHiker",
      "searchable": 1,
      "quickSearch": 1,
      "filterable": 1,
      "ext": "./json/DJyyyyw.json"
    },
    {
      "key": "csp_xpath_kuqimv",
      "name": "🎤酷奇MV",
      "type": 3,
      "api": "csp_XPath",
      "searchable": 1,
      "quickSearch": 1,
      "filterable": 1,
      "ext": "./json/kuqimv.json"
    },
    {
      "key": "MTV",
      "name": "🎧明星┃MV",
      "type": 3,
      "api": "csp_Bili",
      "style": {
        "type": "rect",
        "ratio": 1.597
      },
      "searchable": 0,
      "quickSearch": 0,
      "changeable": 0,
      "ext": "./json/MTV.json"
    },
    {
      "key": "js_a8音乐",
      "name": "🎸A8音乐",
      "type": 3,
      "api": "./drpy2.min.js",
      "searchable": 1,
      "quickSearch": 1,
      "filterable": 1,
      "ext": "./js/a8yy.js"
    }
  ],
  "parses": [
    {
      "name": "Web聚合",
      "type": 3,
      "url": "Web"
    },
    {
      "name": "开心",
      "type": 1,
      "url": "http://119.91.123.253:2345/Api/yun.php?url="
    },
    {
      "name": "影视",
      "type": 1,
      "url": "http://122.228.84.103:7777/api/?key=rSqUtltpbfk1xsQFjz&url="
    },
    {
      "name": "解析",
      "type": 1,
      "url": "http://119.91.123.253:2345/Api/yun.php?url=",
      "ext": {
        "flag": [
          "qq",
          "腾讯",
          "企鹅",
          "IQiYi",
          "qiyi",
          "爱奇艺",
          "奇艺",
          "youku",
          "YouKu",
          "优酷",
          "sohu",
          "SoHu",
          "搜狐",
          "letv",
          "LeShi",
          "乐视",
          "imgo",
          "mgtv",
          "MangGuo",
          "芒果",
          "SLYS4k",
          "BYGA",
          "luanzi",
          "AliS",
          "dxzy",
          "bilibili",
          "QEYSS",
          "xigua",
          "西瓜视频",
          "腾讯视频",
          "奇艺视频",
          "优酷视频",
          "芒果视频",
          "乐视视频"
        ],
        "header": {
          "User-Agent": "Dart/2.18 (dart:io)"
        }
      }
    },
    {
      "name": "极速解析",
      "type": 1,
      "url": "https://api.json.icu/api/?key=0bfb59b5928233f5665db10ebcade96f&url=",
      "ext": {
        "flag": [
          "qq",
          "腾讯",
          "企鹅",
          "IQiYi",
          "qiyi",
          "爱奇艺",
          "奇艺",
          "youku",
          "YouKu",
          "优酷",
          "sohu",
          "SoHu",
          "搜狐",
          "letv",
          "LeShi",
          "乐视",
          "imgo",
          "mgtv",
          "MangGuo",
          "芒果",
          "SMD",
          "YuMi",
          "luanzi",
          "AliS",
          "dxzy",
          "bilibili",
          "QEYSS",
          "xigua",
          "西瓜视频",
          "腾讯视频",
          "奇艺视频",
          "优酷视频",
          "芒果视频",
          "乐视视频"
        ],
        "header": {
          "User-Agent": "Dart/2.18 (dart:io)"
        }
      }
    },
    {
      "name": "️快乐",
      "type": 0,
      "url": "https://api.tyun77.cn/api.php/provide/parseDicturl?url="
    },
    {
      "name": "77",
      "type": 0,
      "url": "https://jx.jsonplayer.com/player/?url=",
      "flag": [
        "qq",
        "腾讯",
        "qiyi",
        "爱奇艺",
        "奇艺",
        "youku",
        "优",
        "mgtv",
        "芒果",
        "letv",
        "leshi",
        "LS",
        "乐视",
        "pptv",
        "PPTV",
        "sohu",
        "bilibili",
        "哔哩哔哩",
        "哔哩"
      ]
    },
    {
      "name": "爱酷",
      "type": 1,
      "url": "http://42.157.129.139:7788/json/aiku.php?url=",
      "ext": {
        "flag": [
          "seven",
          "mgtv",
          "qiyi",
          "imgo",
          "爱奇艺",
          "奇艺",
          "qq",
          "腾讯",
          "youku",
          "优酷",
          "pptv",
          "PPTV",
          "letv",
          "乐视",
          "leshi",
          "bilibili",
          "哔哩哔哩",
          "哔哩",
          "mgtv",
          "芒果",
          "芒果"
        ],
        "header": {
          "User-Agent": "Lavf/58.12.100"
        }
      }
    },
    {
      "name": "m3u8嗅探",
      "type": 0,
      "url": "https://jx.m3u8.tv/jiexi/?url=",
      "ext": {
        "flag": [
          "qq",
          "腾讯",
          "qiyi",
          "iqiyi",
          "爱奇艺",
          "奇艺",
          "youku",
          "yk",
          "优酷",
          "mgtv",
          "imgo",
          "芒果"
        ]
      }
    },
    {
      "name": "秀探",
      "type": 0,
      "url": "https://jx.xmflv.com/?url="
    },
    {
      "name": "-嗅探-",
      "type": 0,
      "url": "https://jx.xyflv.cc/?url=",
      "ext": {
        "header": {
          "user-agent": "Mozilla/5.0 (Linux; Android 13; V2049A Build/TP1A.220624.014; wv) AppleWebKit/537.36 (KHTML, like Gecko) Version/4.0 Chrome/116.0.0.0 Mobile Safari/537.36",
          "referer": "https://www.xyflv.cc/"
        }
      }
    },
    {
      "name": "虾米",
      "type": 0,
      "url": "https://jx.xmflv.com/?url=",
      "ext": {
        "flag": [
          "qq",
          "腾讯",
          "qiyi",
          "爱奇艺",
          "奇艺",
          "youku",
          "优酷",
          "sohu",
          "搜狐",
          "letv",
          "乐视",
          "mgtv",
          "芒果",
          "imgo",
          "rx",
          "ltnb",
          "bilibili",
          "1905",
          "xigua"
        ]
      }
    },
    {
      "name": "夜幕",
      "type": 0,
      "url": "https://www.yemu.xyz/?url=",
      "ext": {
        "flag": [
          "qq",
          "腾讯",
          "qiyi",
          "iqiyi",
          "爱奇艺",
          "奇艺",
          "youku",
          "优酷",
          "mgtv",
          "芒果",
          "letv",
          "乐视",
          "pptv",
          "PPTV",
          "sohu",
          "bilibili",
          "哔哩哔哩",
          "哔哩"
        ]
      }
    },
    {
      "name": "️绣探",
      "type": 0,
      "url": "https://www.pangujiexi.com/pangu/?url="
    },
    {
      "name": "嗅探",
      "type": 0,
      "url": "https://jx.jsonplayer.com/player/?=&url=",
      "ext": {
        "flag": [
          "qq",
          "腾讯",
          "qiyi",
          "iqiyi",
          "爱奇艺",
          "奇艺",
          "youku",
          "yk",
          "优酷",
          "mgtv",
          "imgo",
          "芒果"
        ]
      }
    },
    {
      "name": "7777嗅探",
      "type": 0,
      "url": "https://jx.777jiexi.com/player/?url="
    },
    {
      "name": "杰森嗅探",
      "type": 0,
      "url": "https://jx.jsonplayer.com/player/?url="
    },
    {
      "name": "vip嗅探",
      "type": 0,
      "url": "https://vip.lianfaka.com/vip/?url=",
      "ext": {
        "flag": [
          "qq",
          "腾讯",
          "qiyi",
          "爱奇艺",
          "奇艺",
          "youku",
          "优酷",
          "mgtv",
          "芒果",
          "imgo",
          "letv",
          "乐视",
          "pptv",
          "PPTV",
          "sohu",
          "bilibili",
          "哔哩哔哩",
          "哔哩"
        ],
        "header": {
          "User-Agent": "okhttp/4.1.0"
        }
      }
    },
    {
      "name": "8090嗅探",
      "type": 0,
      "url": "https://www.8090g.cn/jiexi/?url="
    },
    {
      "name": "m3u8嗅探",
      "type": 0,
      "url": "https://jx.m3u8.tv/jiexi/?url=",
      "ext": {
        "flag": [
          "qq",
          "腾讯",
          "qiyi",
          "iqiyi",
          "爱奇艺",
          "奇艺",
          "youku",
          "yk",
          "优酷",
          "mgtv",
          "imgo",
          "芒果"
        ]
      }
    },
    {
      "name": "-虾米-",
      "type": 0,
      "url": "https://jx.xmflv.com/?url=",
      "ext": {
        "header": {
          "user-agent": "Mozilla/5.0 (Windows NT 10.0; Win64; x64) AppleWebKit/537.36 (KHTML, like Gecko) Chrome/110.0.0.0 Safari/537.36 Edg/110.0.1587.57"
        }
      }
    },
    {
      "name": "-爱酷-",
      "type": 0,
      "url": "https://jx.zhanlangbu.com/?url=",
      "ext": {
        "flag": [
          "qq",
          "腾讯",
          "qiyi",
          "爱奇艺",
          "奇艺",
          "youku",
          "优酷",
          "mgtv",
          "芒果",
          "letv",
          "乐视",
          "pptv",
          "PPTV",
          "sohu",
          "bilibili",
          "哔哩哔哩",
          "哔哩"
        ],
        "ext": {
          "header": {
            "user-agent": "Mozilla/5.0 (Linux; Android 13; V2049A Build/TP1A.220624.014; wv) AppleWebKit/537.36 (KHTML, like Gecko) Version/4.0 Chrome/116.0.0.0 Mobile Safari/537.36"
          }
        }
      }
    },
    {
      "name": "-云解析-",
      "type": 0,
      "url": "https://jx.yparse.com/index.php?url=",
      "ext": {
        "header": {
          "user-agent": "Mozilla/5.0 (Linux; Android 13; V2049A Build/TP1A.220624.014; wv) AppleWebKit/537.36 (KHTML, like Gecko) Version/4.0 Chrome/116.0.0.0 Mobile Safari/537.36"
        }
      }
    },
    {
      "name": "-剖云-",
      "type": 0,
      "url": "https://www.kkvip2022.com/vip/jiexi1/?url=",
      "ext": {
        "header": {
          "user-agent": "Mozilla/5.0 (Linux; Android 13; V2049A Build/TP1A.220624.014; wv) AppleWebKit/537.36 (KHTML, like Gecko) Version/4.0 Chrome/116.0.0.0 Mobile Safari/537.36"
        }
      }
    },
    {
      "name": "-全看-",
      "type": 0,
      "url": "https://jx.quankan.app/?url=",
      "ext": {
        "header": {
          "user-agent": "Mozilla/5.0 (Linux; Android 13; V2049A Build/TP1A.220624.014; wv) AppleWebKit/537.36 (KHTML, like Gecko) Version/4.0 Chrome/116.0.0.0 Mobile Safari/537.36"
        }
      }
    },
    {
      "name": "-爱豆-",
      "type": 0,
      "url": "https://jx.aidouer.net/?url=",
      "ext": {
        "header": {
          "user-agent": "Mozilla/5.0 (Linux; Android 13; V2049A Build/TP1A.220624.014; wv) AppleWebKit/537.36 (KHTML, like Gecko) Version/4.0 Chrome/116.0.0.0 Mobile Safari/537.36",
          "referer": "https://jiejie.uk/"
        }
      }
    }
  ],
  "flags": [
    "youku",
    "qq",
    "iqiyi",
    "qiyi",
    "letv",
    "sohu",
    "tudou",
    "pptv",
    "mgtv",
    "wasu",
    "bilibili",
    "renrenmi"
  ],
  "rules": [
    {
      "host": "www.iesdouyin.com",
      "rule": [
        "playwm/?video_id="
      ]
    },
    {
      "host": "www.ysgc.vip",
      "rule": [
        "getm3u8?url=http"
      ]
    },
    {
      "host": "v.douyin.com",
      "rule": [
        "playwm/?video_id="
      ]
    },
    {
      "host": "dyxs20.com",
      "rule": [
        ".m3u8"
      ]
    },
    {
      "host": "www.agemys.cc",
      "rule": [
        "cdn-tos",
        "obj/tos-cn"
      ]
    },
    {
      "host": "www.sharenice.net",
      "rule": [
        "http.*?/play.{0,3}\\?[^url]{2,8}=.*",
        "qianpailive.com",
        "vid="
      ]
    },
    {
      "name": "暴风",
      "hosts": [
        "bfzy",
        "bfbfvip"
      ],
      "regex": [
        "#EXTINF.*?\\s+.*?adjump.*?\\.ts\\s+"
      ]
    },
    {
      "name": "量子",
      "hosts": [
        "vip.lz",
        "hd.lz",
        ".cdnlz"
      ],
      "regex": [
        "#EXT-X-DISCONTINUITY\\r*\\n*#EXTINF:6\\.666667,[\\s\\S]*?#EXT-X-DISCONTINUITY",
        "#EXTINF.*?\\s+.*?1o.*?\\.ts\\s+"
      ]
    },
    {
      "name": "非凡",
      "hosts": [
        "vip.ffzy",
        "hd.ffzy"
      ],
      "regex": [
        "20.52",
        "#EXT-X-DISCONTINUITY\\r*\\n*#EXTINF:7\\.400000,[\\s\\S]*?#EXT-X-DISCONTINUITY",
        "#EXTINF.*?\\s+.*?1170(20|32).*?\\.ts\\s+",
        "#EXTINF.*?\\s+.*?116977.*?\\.ts\\s+"
      ]
    },
    {
      "name": "索尼",
      "hosts": [
        "suonizy"
      ],
      "regex": [
        "#EXT-X-DISCONTINUITY\\r*\\n*#EXTINF:1\\.000000,[\\s\\S]*?#EXT-X-DISCONTINUITY",
        "#EXTINF.*?\\s+.*?p1ayer.*?\\.ts\\s+",
        "#EXTINF.*?\\s+.*?\\/video\\/original.*?\\.ts\\s+"
      ]
    },
    {
      "name": "快看",
      "hosts": [
        "kuaikan"
      ],
      "regex": [
        "#EXT-X-KEY:METHOD=NONE\\r*\\n*#EXTINF:5,[\\s\\S]*?#EXT-X-DISCONTINUITY",
        "#EXT-X-KEY:METHOD=NONE\\r*\\n*#EXTINF:2\\.4,[\\s\\S]*?#EXT-X-DISCONTINUITY"
      ]
    },
    {
      "name": "海外看",
      "hosts": [
        "haiwaikan"
      ],
      "regex": [
        "10.0099",
        "10.3333",
        "16.0599",
        "8.1748",
        "10.85"
      ]
    },
    {
      "name": "磁力广告",
      "hosts": [
        "magnet"
      ],
      "regex": [
        "更多",
        "社 區",
        "x u u",
        "最 新",
        "更 新",
        "社 区",
        "有趣",
        "有 趣",
        "英皇体育",
        "全中文AV在线",
        "澳门皇冠赌场",
        "哥哥快来",
        "美女荷官",
        "裸聊",
        "新片首发",
        "UUE29"
      ]
    }
  ],
  "ijk": [
    {
      "group": "软解码",
      "options": [
        {
          "category": 4,
          "name": "opensles",
          "value": "0"
        },
        {
          "category": 4,
          "name": "overlay-format",
          "value": "842225234"
        },
        {
          "category": 4,
          "name": "framedrop",
          "value": "1"
        },
        {
          "category": 4,
          "name": "soundtouch",
          "value": "1"
        },
        {
          "category": 4,
          "name": "start-on-prepared",
          "value": "1"
        },
        {
          "category": 1,
          "name": "http-detect-range-support",
          "value": "0"
        },
        {
          "category": 1,
          "name": "fflags",
          "value": "fastseek"
        },
        {
          "category": 2,
          "name": "skip_loop_filter",
          "value": "48"
        },
        {
          "category": 4,
          "name": "reconnect",
          "value": "1"
        },
        {
          "category": 4,
          "name": "enable-accurate-seek",
          "value": "0"
        },
        {
          "category": 4,
          "name": "mediacodec",
          "value": "0"
        },
        {
          "category": 4,
          "name": "mediacodec-auto-rotate",
          "value": "0"
        },
        {
          "category": 4,
          "name": "mediacodec-handle-resolution-change",
          "value": "0"
        },
        {
          "category": 4,
          "name": "mediacodec-hevc",
          "value": "0"
        },
        {
          "category": 1,
          "name": "dns_cache_timeout",
          "value": "600000000"
        }
      ]
    },
    {
      "group": "硬解码",
      "options": [
        {
          "category": 4,
          "name": "opensles",
          "value": "0"
        },
        {
          "category": 4,
          "name": "overlay-format",
          "value": "842225234"
        },
        {
          "category": 4,
          "name": "framedrop",
          "value": "1"
        },
        {
          "category": 4,
          "name": "soundtouch",
          "value": "1"
        },
        {
          "category": 4,
          "name": "start-on-prepared",
          "value": "1"
        },
        {
          "category": 1,
          "name": "http-detect-range-support",
          "value": "0"
        },
        {
          "category": 1,
          "name": "fflags",
          "value": "fastseek"
        },
        {
          "category": 2,
          "name": "skip_loop_filter",
          "value": "48"
        },
        {
          "category": 4,
          "name": "reconnect",
          "value": "1"
        },
        {
          "category": 4,
          "name": "enable-accurate-seek",
          "value": "0"
        },
        {
          "category": 4,
          "name": "mediacodec",
          "value": "1"
        },
        {
          "category": 4,
          "name": "mediacodec-auto-rotate",
          "value": "1"
        },
        {
          "category": 4,
          "name": "mediacodec-handle-resolution-change",
          "value": "1"
        },
        {
          "category": 4,
          "name": "mediacodec-hevc",
          "value": "1"
        },
        {
          "category": 1,
          "name": "dns_cache_timeout",
          "value": "600000000"
        }
      ]
    }
  ],
  "ads": [
    "mimg.0c1q0l.cn",
    "www.googletagmanager.com",
    "www.google-analytics.com",
    "mc.usihnbcq.cn",
    "mg.g1mm3d.cn",
    "mscs.svaeuzh.cn",
    "cnzz.hhttm.top",
    "tp.vinuxhome.com",
    "cnzz.mmstat.com",
    "www.baihuillq.com",
    "s23.cnzz.com",
    "z3.cnzz.com",
    "c.cnzz.com",
    "stj.v1vo.top",
    "z12.cnzz.com",
    "img.mosflower.cn",
    "tips.gamevvip.com",
    "ehwe.yhdtns.com",
    "xdn.cqqc3.com",
    "www.jixunkyy.cn",
    "sp.chemacid.cn",
    "hm.baidu.com",
    "s9.cnzz.com",
    "z6.cnzz.com",
    "um.cavuc.com",
    "mav.mavuz.com",
    "wofwk.aoidf3.com",
    "z5.cnzz.com",
    "xc.hubeijieshikj.cn",
    "tj.tianwenhu.com",
    "xg.gars57.cn",
    "k.jinxiuzhilv.com",
    "cdn.bootcss.com",
    "ppl.xunzhuo123.com",
    "xomk.jiangjunmh.top",
    "img.xunzhuo123.com",
    "z1.cnzz.com",
    "s13.cnzz.com",
    "xg.huataisangao.cn",
    "z7.cnzz.com",
    "xg.huataisangao.cn",
    "z2.cnzz.com",
    "s96.cnzz.com",
    "q11.cnzz.com",
    "thy.dacedsfa.cn",
    "xg.whsbpw.cn",
    "s19.cnzz.com",
    "z8.cnzz.com",
    "s4.cnzz.com",
    "f5w.as12df.top",
    "ae01.alicdn.com",
    "www.92424.cn",
    "k.wudejia.com",
    "vivovip.mmszxc.top",
    "qiu.xixiqiu.com",
    "cdnjs.hnfenxun.com",
    "cms.qdwght.com",
    "api.htpan.net"
  ]
}
